mongodb_connect/__init__.py
mongodb_connect/mongo_crud.py
mahesh_mongodb_connect-1.0.4.dist-info/METADATA
mahesh_mongodb_connect-1.0.4.dist-info/WHEEL
mahesh_mongodb_connect-1.0.4.dist-info/top_level.txt
mahesh_mongodb_connect-1.0.4.dist-info/RECORD
